{
  "project_info": {
    "project_number": "445543926352",
    "project_id": "my-ecom-project01-9486a",
    "storage_bucket": "my-ecom-project01-9486a.appspot.com"
  },
  "client": [
    {
      "client_info": {
        "mobilesdk_app_id": "1:445543926352:android:a11d4744394f39d886df55",
        "android_client_info": {
          "package_name": "com.example.e_commerce_app"
        }
      },
      "oauth_client": [],
      "api_key": [
        {
          "current_key": "AIzaSyC2BpgKo7bowkGvZi4ukS5cvTwmSW_jyrU"
        }
      ],
      "services": {
        "appinvite_service": {
          "other_platform_oauth_client": []
        }
      }
    },
    {
      "client_info": {
        "mobilesdk_app_id": "1:445543926352:android:57b46bbc8d2d3df786df55",
        "android_client_info": {
          "package_name": "com.example.e_commerce_user_app"
        }
      },
      "oauth_client": [],
      "api_key": [
        {
          "current_key": "AIzaSyC2BpgKo7bowkGvZi4ukS5cvTwmSW_jyrU"
        }
      ],
      "services": {
        "appinvite_service": {
          "other_platform_oauth_client": []
        }
      }
    }
  ],
  "configuration_version": "1"
}